{
  "app": "radarr",
  "base": false,
  "testMuteCmd": false,
  "channels": [
    {
      "name": "stable",
      "metavar": "",
      "renovate::dataSource": "docker",
      "renovate::depName": "ghcr.io/onedr0p/radarr",
      "renovate::versioning": "loose",
      "version": "5.19.3.9730",
      "platforms": [
        "linux/amd64",
        "linux/arm64"
      ]
    }, {
      "name": "devel",
      "metavar": "-develop",
      "renovate::dataSource": "docker",
      "renovate::depName": "ghcr.io/onedr0p/radarr-develop",
      "renovate::versioning": "loose",
      "version": "5.20.0.9752",
      "platforms": [
        "linux/amd64",
        "linux/arm64"
      ]
    }, {
      "name": "nightly",
      "metavar": "-nightly",
      "renovate::dataSource": "docker",
      "renovate::depName": "ghcr.io/onedr0p/radarr-nightly",
      "renovate::versioning": "loose",
      "version": "5.20.1.9770",
      "platforms": [
        "linux/amd64",
        "linux/arm64"
      ]
    }
  ]
}
